LICENSE
MANIFEST.in
README.md
setup.cfg
setup.py
cytohmm.egg-info/PKG-INFO
cytohmm.egg-info/SOURCES.txt
cytohmm.egg-info/dependency_links.txt
cytohmm.egg-info/not-zip-safe
cytohmm.egg-info/requires.txt
cytohmm.egg-info/top_level.txt
docs/hmm-solutions.pdf
src/cytohmm/__init__.py
src/cytohmm/likelihood.c
src/cytohmm/likelihood.pyx
src/cytohmm/markov_chain.c
src/cytohmm/markov_chain.pyx
src/cytohmm/sequence_segmenter.py